rpc3/README.rst
rpc3/__init__.py
rpc3/rpc3.py
rpc3/img/file_structure.png
rpc3/img/key_values.png
rpc3/img/multiplex.png
rpc3/img/multiplex_2.png
rpc3/img/names.png
rpc3/img/time_history_table_1.png
rpc3/img/time_history_table_2.png
rpc3/img/time_history_table_3.png
rpc3/tests/__init__.py
rpc3/tests/test_rpc3.py
rpc3_file-1.0.0rc5.dist-info/licenses/LICENSE
rpc3_file-1.0.0rc5.dist-info/METADATA
rpc3_file-1.0.0rc5.dist-info/WHEEL
rpc3_file-1.0.0rc5.dist-info/top_level.txt
rpc3_file-1.0.0rc5.dist-info/RECORD
