Metadata-Version: 2.4
Name: rpc3-file
Version: 1.0.0rc5
Summary: Read/write access to data files in RPC3 file format.
Home-page: http://github.com/a-ma72/rpc3-file
Author: Andreas Martin
License: BSD-2-Clause License
Classifier: Development Status :: 6 - Mature
Classifier: Environment :: Console
Classifier: Framework :: Buildout :: Extension
Classifier: Intended Audience :: Developers
Classifier: Intended Audience :: Education
Classifier: Intended Audience :: Information Technology
Classifier: Intended Audience :: Science/Research
Classifier: Natural Language :: English
Classifier: Operating System :: MacOS :: MacOS X
Classifier: Operating System :: Microsoft :: Windows
Classifier: Operating System :: POSIX
Classifier: Programming Language :: Python :: 3
Classifier: Topic :: Scientific/Engineering
Classifier: Topic :: Scientific/Engineering :: Information Analysis
Requires-Python: >=3.7
License-File: LICENSE
Requires-Dist: numpy>=1.19
Requires-Dist: tqdm
Dynamic: author
Dynamic: classifier
Dynamic: description
Dynamic: description-content-type
Dynamic: home-page
Dynamic: license
Dynamic: license-file
Dynamic: requires-dist
Dynamic: requires-python
Dynamic: summary
